pk_model/__init__.py
pk_model/definitions.py
pk_model/dosing.py
pk_model/solver.py
pk_model/ux.py
pk_model/visualiser.py
oxbiodtp_7_PK_modelling-1.0.0.dist-info/LICENSE
oxbiodtp_7_PK_modelling-1.0.0.dist-info/METADATA
oxbiodtp_7_PK_modelling-1.0.0.dist-info/WHEEL
oxbiodtp_7_PK_modelling-1.0.0.dist-info/top_level.txt
oxbiodtp_7_PK_modelling-1.0.0.dist-info/RECORD
