Metadata-Version: 2.1
Name: oxbiodtp-7-PK-modelling
Version: 1.0.0
Summary: 'Library for producing, solving and visualising pharmacokinetic models.'
Home-page: https://github.com/Software-Engineering-BBSRC-Group-6/PK_modelling
Author: 'Dan Hudson, Ishaan Kapoor, Sam Johnson, Amit Halkhoree, Cameron Anderson, Joe Pollacco'
Author-email: joseph.pollacco@dtc.ox.ac.uk
License: MIT
Keywords: pharmokinetic,pharmacokinetic,compartment,ODE
Platform: UNKNOWN
Classifier: Programming Language :: Python :: 3.9
Requires-Dist: attrs (==21.2.0)
Requires-Dist: certifi (==2021.10.8)
Requires-Dist: charset-normalizer (==2.0.7)
Requires-Dist: codecov (==2.1.12)
Requires-Dist: coverage (==6.0.2)
Requires-Dist: cycler (==0.10.0)
Requires-Dist: flake8 (==4.0.1)
Requires-Dist: idna (==3.3)
Requires-Dist: iniconfig (==1.1.1)
Requires-Dist: kiwisolver (==1.3.2)
Requires-Dist: matplotlib (==3.4.3)
Requires-Dist: mccabe (==0.6.1)
Requires-Dist: numpy (==1.21.2)
Requires-Dist: packaging (==21.0)
Requires-Dist: Pillow (==8.4.0)
Requires-Dist: pluggy (==1.0.0)
Requires-Dist: py (==1.10.0)
Requires-Dist: pycodestyle (==2.8.0)
Requires-Dist: pyflakes (==2.4.0)
Requires-Dist: pyparsing (==2.4.7)
Requires-Dist: pytest (==6.2.5)
Requires-Dist: python-dateutil (==2.8.2)
Requires-Dist: requests (==2.26.0)
Requires-Dist: sympy (==1.6.2)
Requires-Dist: scipy (==1.7.1)
Requires-Dist: six (==1.16.0)
Requires-Dist: toml (==0.10.2)
Requires-Dist: urllib3 (==1.26.7)
